{"chunk_definitions":[{"row":24,"row_count":1,"visible":true,"expansion_state":0,"options":{"engine":"r","label":"setup","include":false,"dev":"png"},"document_id":"79EAEAA5","chunk_id":"csetup_chunk","chunk_label":"setup"},{"row":29,"row_count":1,"visible":true,"expansion_state":0,"options":{"engine":"r","label":"options","include":false,"dev":"png"},"document_id":"79EAEAA5","chunk_id":"ciywbb8qx1q4i","chunk_label":"options"},{"row":43,"row_count":1,"visible":true,"expansion_state":0,"options":{"engine":"r","label":"unnamed-chunk-3","dev":"png"},"document_id":"79EAEAA5","chunk_id":"cyo5g3s3i00am","chunk_label":"unnamed-chunk-1"},{"row":63,"row_count":1,"visible":true,"expansion_state":0,"options":{"engine":"r","label":"load-packages","eval":false,"dev":"png"},"document_id":"79EAEAA5","chunk_id":"cvywsci4jgxtf","chunk_label":"load-packages"},{"row":82,"row_count":1,"visible":true,"expansion_state":0,"options":{"engine":"r","label":"unnamed-chunk-4","dev":"png"},"document_id":"79EAEAA5","chunk_id":"cz4e5ilnn9vx1","chunk_label":"unnamed-chunk-2"},{"row":93,"row_count":1,"visible":true,"expansion_state":0,"options":{"engine":"r","label":"q3-task","dev":"png"},"document_id":"79EAEAA5","chunk_id":"c79pm25d8z6bt","chunk_label":"q3-task"},{"row":124,"row_count":1,"visible":true,"expansion_state":0,"options":{"engine":"r","label":"pipe-example","dev":"png"},"document_id":"79EAEAA5","chunk_id":"ck468jba0hr3o","chunk_label":"pipe-example"}],"doc_write_time":1737669475}